extended_algo/__init__.py
extended_algo/engine/OrderDetails.py
extended_algo/engine/VectorStrategy.py
extended_algo/engine/create_audit_file.py
extended_algo/engine/create_consolidated_stats.py
extended_algo/engine/create_limit_entries.py
extended_algo/engine/create_stop_entries.py
extended_algo/market/LogReturnMarketData.py
extended_algo/market/MarketData.py
extended_algo/market/SecurityMaster.py
extended_algo/market/__init__.py
extended_algo/market/style/TickBars.py
extended_algo/market/style/TickDollarBars.py
extended_algo/market/style/TickRangeBars.py
extended_algo/market/style/TickVolumeBars.py
extended_algo/market/style/Ticks.py
extended_algo/market/style/TimeBars.py
extended_algo/market/style/__init__.py
extended_algo/market/utils/common.py
extended_algo/market/utils/move_remote_to_local.py
extended_algo/market/utils/resample_market_data.py
extended_algo/market/utils/symbol_lookup.py
extended_algo/market/utils/use_cached_market_data.py
extended_algo/report/CalculatePnLStats.py
extended_algo/report/ConstructPortfolioOfStrategies.py
extended_algo/report/calculate/Features.py
extended_algo/report/calculate/MaeMfe.py
extended_algo/report/calculate/Pnl.py
extended_algo/report/calculate/Stats.py
extended_algo/report/utils/read_strategy_metadata.py
extended_algo-0.1.6.2.dist-info/METADATA
extended_algo-0.1.6.2.dist-info/WHEEL
extended_algo-0.1.6.2.dist-info/top_level.txt
extended_algo-0.1.6.2.dist-info/RECORD
