Metadata-Version: 2.1
Name: extended-algo
Version: 0.1.6.2
Summary: wrapper for creating event and vector algo that supports the extended-chart
Home-page: https://github.com/karunkrishna/extended_algo
Author: Karun Krishna
Author-email: karun.krishna@gmail.com
License: MIT
Requires-Dist: pandas
Requires-Dist: python-dotenv
Requires-Dist: pandas-ta
Requires-Dist: extended-chart
Requires-Dist: tqdm
Requires-Dist: pyarrow
Requires-Dist: SQLAlchemy
Requires-Dist: mysqlclient
